copperhead/__init__.py
copperhead/__version__.py
copperhead/code_generator.py
copperhead/default_config.py
copperhead/module_generator.py
copperhead/setup_generator.py
copperhead/templates/__init__.py
copperhead/templates/basic_setup.py
copperhead/templates/basic_wrapper.py
copperhead/templates/cpp_types/__init__.py
copperhead/templates/cpp_types/associative_containers.py
copperhead/templates/cpp_types/collections.py
copperhead/templates/cpp_types/container_adapters.py
copperhead/templates/cpp_types/cpp_type.py
copperhead/templates/cpp_types/primitives.py
copperhead/templates/cpp_types/sequence_containers.py
copperhead/templates/cpp_types/strings.py
copperhead/templates/cpp_types/unordered_associative_containers.py
copperhead-2019.9.0.dist-info/LICENSE.md
copperhead-2019.9.0.dist-info/METADATA
copperhead-2019.9.0.dist-info/WHEEL
copperhead-2019.9.0.dist-info/top_level.txt
copperhead-2019.9.0.dist-info/RECORD
